EnDecrypter/__init__.py
EnDecrypter/binario.py
EnDecrypter/cesar.py
EnDecrypter/monoalfabetico.py
EnDecrypter/polialfabetico.py
EnDecrypter/rc4.py
EnDecrypter/transposicion.py
EnDecrypter/classical/__init__.py
EnDecrypter/classical/caesar.py
EnDecrypter/classical/enigma.py
EnDecrypter/classical/hill.py
EnDecrypter/classical/monoalphabetic.py
EnDecrypter/classical/polyalphabetic.py
EnDecrypter/classical/transposition.py
EnDecrypter/modern/__init__.py
EnDecrypter/modern/chacha20.py
EnDecrypter/modern/des.py
EnDecrypter/modern/rc4.py
EnDecrypter/modern/rc5.py
EnDecrypter/modern/rc6.py
EnDecrypter/modern/salsa20.py
EnDecrypter/modern/triple_des.py
EnDecrypter/utils/__init__.py
EnDecrypter/utils/binary.py
endecrypter-1.20.21.dist-info/LICENSE
endecrypter-1.20.21.dist-info/METADATA
endecrypter-1.20.21.dist-info/WHEEL
endecrypter-1.20.21.dist-info/top_level.txt
endecrypter-1.20.21.dist-info/RECORD
