Metadata-Version: 2.1
Name: endecrypter
Version: 1.20.21
Summary: A comprehensive encryption/decryption library
Home-page: https://github.com/Elabsurdo984/EnDecrypter.git
Author: Elabsurdo984
Author-email: matiassfernandez00@gmail.com
License: GPL
Project-URL: Source, https://github.com/Elabsurdo984/EnDecrypter
Requires-Python: >=3.12
License-File: LICENSE
Requires-Dist: pycryptodome>=3.21.0
Requires-Dist: numpy>=2.2.3
